subdue/__init__.py
subdue/__main__.py
subdue/base_classes.py
subdue/cmd.py
subdue/daqmx.py
subdue/thermocouple.py
subdue/utilities.py
subdue/visa.py
subdue/static/index.md
subdue-0.1.8.dist-info/METADATA
subdue-0.1.8.dist-info/WHEEL
subdue-0.1.8.dist-info/entry_points.txt
subdue-0.1.8.dist-info/top_level.txt
subdue-0.1.8.dist-info/RECORD
