Metadata-Version: 2.1
Name: subdue
Version: 0.1.8
Summary: Hardware manipulation for National Instruments, Agilent, etc.
Home-page: https://github.com/slightlynybbled/subdue
Author: Jason R. Jones
Author-email: slightlynybbled@gmail.com
License: MIT
Keywords: test labview visa instrument hardware
Platform: UNKNOWN
Requires-Dist: eventlet (>=0.21.0)
Requires-Dist: flask (>=0.12)
Requires-Dist: mkdocs (>=0.15.3)
Requires-Dist: numpy (>=1.11.2)
Requires-Dist: pyvisa (>=1.8)
Requires-Dist: pydaqmx (>=1.3.2)
Requires-Dist: pytest (>=3.0.2)
Requires-Dist: waitress (>=1.0.0)
